{
	"parent": "block/block",
	"textures": {
		"3": "block/cactus_flower_1",
		"4": "block/cactus_flower_2",
		"5": "block/cactus_flower_back_1",
		"bottom": "block/cactus_bottom",
		"top": "block/cactus_top",
		"particle": "block/cactus_side",
		"side": "block/cactus_side"
	},
	"elements": [
		{
			"from": [0, 0, 0],
			"to": [16, 16, 16],
			"faces": {
				"up": {"uv": [0, 0, 16, 16], "texture": "#top", "cullface": "up"},
				"down": {"uv": [0, 0, 16, 16], "texture": "#bottom", "cullface": "down"}
			}
		},
		{
			"from": [0, 0, 1],
			"to": [16, 16, 15],
			"faces": {
				"north": {"uv": [0, 0, 16, 16], "texture": "#side"},
				"south": {"uv": [0, 0, 16, 16], "texture": "#side"}
			}
		},
		{
			"from": [1, 0, 0],
			"to": [15, 16, 16],
			"faces": {
				"east": {"uv": [0, 0, 16, 16], "texture": "#side"},
				"west": {"uv": [0, 0, 16, 16], "texture": "#side"}
			}
		},
		{
			"from": [8, 16, 0],
			"to": [24, 16, 16],
			"shade": false,
			"rotation": {"angle": 22.5, "axis": "z", "origin": [8, 16, 0]},
			"faces": {
				"up": {"uv": [0, 0, 16, 16], "rotation": 90, "texture": "#3"},
				"down": {"uv": [0, 16, 16, 0], "rotation": 270, "texture": "#5"}
			}
		},
		{
			"from": [-8, 16, 0],
			"to": [8, 16, 16],
			"shade": false,
			"rotation": {"angle": -22.5, "axis": "z", "origin": [8, 16, 0]},
			"faces": {
				"up": {"uv": [0, 0, 16, 16], "rotation": 270, "texture": "#3"},
				"down": {"uv": [0, 16, 16, 0], "rotation": 90, "texture": "#5"}
			}
		},
		{
			"from": [0, 16, 8],
			"to": [16, 16, 24],
			"shade": false,
			"rotation": {"angle": -22.5, "axis": "x", "origin": [0, 16, 8]},
			"faces": {
				"up": {"uv": [16, 16, 0, 0], "texture": "#3"},
				"down": {"uv": [16, 0, 0, 16], "texture": "#5"}
			}
		},
		{
			"from": [0, 16, -8],
			"to": [16, 16, 8],
			"shade": false,
			"rotation": {"angle": 22.5, "axis": "x", "origin": [0, 16, 8]},
			"faces": {
				"up": {"uv": [0, 0, 16, 16], "texture": "#3"},
				"down": {"uv": [0, 16, 16, 0], "texture": "#5"}
			}
		},
		{
			"from": [8, 16, 0],
			"to": [24, 16, 16],
			"shade": false,
			"rotation": {"angle": 45, "axis": "z", "origin": [8, 16, 0]},
			"faces": {
				"up": {"uv": [0, 0, 16, 16], "rotation": 90, "texture": "#4"},
				"down": {"uv": [0, 16, 16, 0], "rotation": 270, "texture": "#4"}
			}
		},
		{
			"from": [0, 16, 8],
			"to": [16, 16, 24],
			"shade": false,
			"rotation": {"angle": -45, "axis": "x", "origin": [0, 16, 8]},
			"faces": {
				"up": {"uv": [16, 16, 0, 0], "texture": "#4"},
				"down": {"uv": [16, 0, 0, 16], "texture": "#4"}
			}
		},
		{
			"from": [-8, 16, 0],
			"to": [8, 16, 16],
			"shade": false,
			"rotation": {"angle": -45, "axis": "z", "origin": [8, 16, 0]},
			"faces": {
				"up": {"uv": [0, 0, 16, 16], "rotation": 270, "texture": "#4"},
				"down": {"uv": [0, 16, 16, 0], "rotation": 90, "texture": "#4"}
			}
		},
		{
			"from": [0, 16, -8],
			"to": [16, 16, 8],
			"shade": false,
			"rotation": {"angle": 45, "axis": "x", "origin": [0, 16, 8]},
			"faces": {
				"up": {"uv": [0, 0, 16, 16], "texture": "#4"},
				"down": {"uv": [0, 16, 16, 0], "texture": "#4"}
			}
		},
		{
			"from": [8, 16, 7.5],
			"to": [8, 19, 8.5],
			"rotation": {"angle": 0, "axis": "y", "origin": [9, 16, 6.5]},
			"faces": {
				"north": {"uv": [6, 15, 9, 15], "rotation": 90, "texture": "#3"},
				"east": {"uv": [6, 15, 9, 16], "rotation": 90, "texture": "#3"},
				"south": {"uv": [6, 15, 9, 15], "rotation": 90, "texture": "#3"},
				"west": {"uv": [6, 15, 9, 16], "rotation": 90, "texture": "#3"},
				"up": {"uv": [6, 15, 6, 16], "rotation": 90, "texture": "#3"},
				"down": {"uv": [6, 15, 6, 16], "rotation": 270, "texture": "#3"}
			}
		},
		{
			"from": [7.5, 16, 8],
			"to": [8.5, 19, 8],
			"rotation": {"angle": 0, "axis": "y", "origin": [9.5, 16, 9]},
			"faces": {
				"north": {"uv": [6, 15, 9, 16], "rotation": 90, "texture": "#3"},
				"east": {"uv": [6, 15, 9, 15], "rotation": 90, "texture": "#3"},
				"south": {"uv": [6, 15, 9, 16], "rotation": 90, "texture": "#3"},
				"west": {"uv": [6, 15, 9, 15], "rotation": 90, "texture": "#3"},
				"up": {"uv": [6, 15, 6, 16], "rotation": 180, "texture": "#3"},
				"down": {"uv": [6, 15, 6, 16], "rotation": 180, "texture": "#3"}
			}
		}
	]
}